[
  {
    "date": "2025-06-15",
    "checks": [
      {
        "time": "2025-06-15T19:31:50.012Z",
        "online": true
      },
      {
        "time": "2025-06-15T19:35:55.908Z",
        "online": true
      },
      {
        "time": "2025-06-15T19:44:38.217Z",
        "online": true
      },
      {
        "time": "2025-06-15T19:45:29.677Z",
        "online": true
      },
      {
        "time": "2025-06-15T19:54:53.149Z",
        "online": true
      },
      {
        "time": "2025-06-15T20:16:50.791Z",
        "online": true
      }
    ]
  }
]